{
  "schema_version": "3.0",
  "generated_at": "2026-07-06T19:00:00Z",
  "window_start": "2026-07-06",
  "window_end": "2026-07-12",
  "summary": "Revisão a pedido do atleta (com critério de dados, não remoção por remoção): a janela volta a treinar quase todo dia (corrida + força intercalados). Guardrail ACWR em 1,18 (ok) e esforço acumulado dos últimos 3 dias em 103 — dentro do normal histórico do atleta (média 51 ± 50, p90 117), sem sinal de fadiga. Sábado fica como único descanso porque, até lá, o acumulado de 72h (C+corrida+Treino A) deve se aproximar do p90 — decisão revista a cada dia, não uma quota fixa.",
  "indicators": [
    { "label": "Corridas (7 dias)", "value": "0 feitas + 3 previstas (fácil 5 km ter, fácil 5 km qui, longão 8,8 km dom)", "status": "ok" },
    { "label": "Guardrail (ACWR)", "value": "1,18 · ok", "status": "ok" },
    { "label": "Esforço agudo (72h)", "value": "103 (baseline: média 51 ± 50, p90 117) — dentro do normal", "status": "ok" },
    { "label": "Recuperação", "value": "Apple Health parado há 8 dias (última leitura 28/06) — FC repouso e sono cegos para esta janela; guardrail + esforço acumulado assumem o peso da decisão", "status": "warning" },
    { "label": "Força (7 dias)", "value": "1 feita (B, seg) + 2 previstas (C qua, A sex)", "status": "ok" }
  ],
  "days": [
    {
      "date": "2026-07-06",
      "weekday": "Seg",
      "status": "done",
      "items": [
        { "type": "strength", "title": "Treino B — posterior/costas/peito", "detail": "Feito na academia hoje.", "done": true }
      ]
    },
    {
      "date": "2026-07-07",
      "weekday": "Ter",
      "status": "planned",
      "items": [
        {
          "type": "run",
          "title": "Corrida fácil 5 km",
          "detail": "Z2 ~5:50/km — guardrail em ok, treino quase todo dia como o atleta prefere.",
          "done": false
        }
      ]
    },
    {
      "date": "2026-07-08",
      "weekday": "Qua",
      "status": "planned",
      "items": [
        {
          "type": "strength",
          "title": "Treino C — pernas/posterior/core",
          "detail": "48h após o Treino B de segunda (a sequência A→B→C já espaça a perna pesada sozinha). Hack amplitude ≤90°, priorizar Mesa Flexora/Abdutora/Panturrilhas.",
          "done": false
        }
      ]
    },
    {
      "date": "2026-07-09",
      "weekday": "Qui",
      "status": "planned",
      "items": [
        {
          "type": "run",
          "title": "Corrida fácil 5 km",
          "detail": "Z2 ~5:50/km — dia seguinte ao Treino C, sem problema com guardrail ok; parar se houver dor articular (não muscular) no joelho.",
          "done": false
        }
      ]
    },
    {
      "date": "2026-07-10",
      "weekday": "Sex",
      "status": "planned",
      "items": [
        {
          "type": "strength",
          "title": "Treino A — pernas + tríceps",
          "detail": "48h antes do longão de domingo (perna pesada respeitando o mínimo de 48h antes de longão/qualidade). Leg Press amplitude ≤90°.",
          "done": false
        }
      ]
    },
    {
      "date": "2026-07-11",
      "weekday": "Sáb",
      "status": "planned",
      "items": [
        { "type": "rest", "title": "Descanso total", "detail": "Único descanso da janela. Motivo: até esse ponto o esforço acumulado de 72h (Treino C + corrida fácil + Treino A) deve se aproximar do p90 histórico (117) — descanso pela carga real, não por calendário; reavaliar se os dados vierem mais leves.", "done": false }
      ]
    },
    {
      "date": "2026-07-12",
      "weekday": "Dom",
      "status": "planned",
      "items": [
        {
          "type": "run",
          "title": "Longão 8,8 km",
          "detail": "Z2 ~5:50/km — progressão conservadora de 8,03 km para 8,8 km (~10%), guardrail em ok.",
          "done": false
        }
      ]
    }
  ],
  "adaptations": [
    "Revisão de critério a pedido do atleta (06/07/2026): descanso deixou de ser quota fixa E deixou de ser removido sem avaliação — agora é decidido por dados, em ordem de prioridade: dor articular > guardrail ACWR > esforço acumulado de 72h (vs. baseline histórica) > FC de repouso/sono (quando atualizados). Critério documentado em ambas as skills.",
    "Esforço acumulado dos últimos 3 dias (07/04-07/06) = 103, dentro da baseline histórica do atleta (média 51, desvio 50, p90 117 numa janela de 3 dias) — não há sinal de fadiga acumulada, então Treino A (sexta) e as corridas fáceis de terça/quinta foram reincluídos sem corte.",
    "Apple Health parado há 8 dias (última leitura 28/06) — sinais de FC de repouso e sono ficam cegos nesta janela. Sem esse dado, o guardrail ACWR (1,18, ok) e o esforço acumulado assumem mais peso na decisão; se o export voltar a sincronizar, esses sinais reentram na avaliação diária.",
    "Sábado mantido como único descanso da janela: previsão de que o acumulado de 72h (Treino C + corrida + Treino A) chegue perto do p90 histórico até lá — decisão pela carga esperada, reavaliada quando os treinos acontecerem de verdade, não uma regra de calendário.",
    "Guardrail de corrida segue em 1,18 (ok); longão de domingo mantido em 8,8 km (progressão de ~10% sobre os 8,03 km de sábado passado)."
  ],
  "coaches": {
    "running": "Guardrail em 1,18 (ok) e esforço acumulado de 72h em 103 (baseline p90 = 117) — nenhum sinal de fadiga. Reincluí as corridas fáceis de terça e quinta e o longão de domingo sobe para 8,8 km. Recuperação via Apple Health está cega (8 dias sem dado), então sigo apoiado no ACWR + esforço.",
    "strength": "Treino A de volta para sexta — sem sinal de esforço acumulado elevado nem dor articular relatada, não há razão para cortar. A rotação A→B→C já dá 48h entre sessões de perna pesada sozinha (seg/qua/sex). Sábado fica de descanso porque a carga prevista de 72h (C+corrida+A) deve chegar perto do teto histórico do atleta até lá."
  }
}
